classeviva/__init__.py
classeviva/cli.py
classeviva/client.py
classeviva/credentials.py
classeviva/model.py
classeviva_client-0.0.7.data/scripts/classeviva
tests/cli/__init__.py
tests/cli/test_agenda.py
tests/cli/test_exceptions.py
tests/cli/test_grades.py
classeviva_client-0.0.7.dist-info/METADATA
classeviva_client-0.0.7.dist-info/WHEEL
classeviva_client-0.0.7.dist-info/top_level.txt
classeviva_client-0.0.7.dist-info/RECORD
