Metadata-Version: 2.1
Name: classeviva-client
Version: 0.0.7
Summary: Python library and a CLI tool to access the https://web.spaggiari.eu
Home-page: https://github.com/zmoog/classeviva-client
Author: Maurizio Branca
Author-email: maurizio.branca@gmail.com
License: UNKNOWN
Platform: UNKNOWN
Classifier: Development Status :: 4 - Beta
Classifier: Intended Audience :: Developers
Classifier: Programming Language :: Python :: 3
Classifier: License :: OSI Approved :: Apache Software License
Classifier: Operating System :: OS Independent
Requires-Dist: pydantic (>=1.9.0)
Requires-Dist: requests (>=2.25.1)
Requires-Dist: click (>=7.1.2)
